COPYING
README
ez_setup.py
setup.py
clipartbrowser/__init__.py
clipartbrowser/browser.py
clipartbrowser/gui.glade
clipartbrowser/ocal.py
clipartbrowser/repository.py
clipartbrowser.egg-info/PKG-INFO
clipartbrowser.egg-info/SOURCES.txt
clipartbrowser.egg-info/dependency_links.txt
clipartbrowser.egg-info/entry_points.txt
clipartbrowser.egg-info/requires.txt
clipartbrowser.egg-info/top_level.txt
