Metadata-Version: 1.0
Name: clipartbrowser
Version: 0.5a1
Summary: A gtk browser for the Open Clipart Library
Home-page: http://code.google.com/p/clipartbrowser
Author: Greg Steffensen
Author-email: greg.steffensen@gmail.com
License: GPL
Keywords: clipart art clipartbrowser ocal images
Platform: UNKNOWN
